{
  "name": "Lumina",
  "short_name": "Lumina",
  "version": "0.7.0-SOVEREIGN",
  "edition": "Shekinah Realization: Sovereign Dominion (Phase 5.0)",
  "build": "zion-lattice-sovereign-final",
  "description": "The world's first AI-integrated spiritual sanctuary. Phase 5.0: Sovereign Dominion and Marketplace Command.",
  "theme_color": "#0f1018",
  "background_color": "#0f1018",
  "display": "standalone",
  "orientation": "portrait",
  "scope": "/",
  "start_url": "/",
  "requestFramePermissions": [
    "camera",
    "microphone",
    "geolocation"
  ]
}